MANIFEST.in
README.md
setup.cfg
setup.py
pyhoofinance/__init__.py
pyhoofinance/defs.py
pyhoofinance/historicdata.py
pyhoofinance/quotedata.py
pyhoofinance.egg-info/PKG-INFO
pyhoofinance.egg-info/SOURCES.txt
pyhoofinance.egg-info/dependency_links.txt
pyhoofinance.egg-info/top_level.txt
test/tests.py