Metadata-Version: 1.0
Name: pyhoofinance
Version: 0.2.3
Summary: Set of functions for retreiving equity data from Yahoo finance
Home-page: https://github.com/innes213/pyhoofinance
Author: Rob Innes Hislop
Author-email: robinneshislop_at_gmail.com
License: GNU LGPL License
Platform: UNKNOWN
